{
  "forms": [
    {
      "id": "default-form",
      "name": "Основная форма",
      "title": "Оставить заявку",
      "subtitle": "Мы свяжемся с вами в течение ",
      "fields": [
        {
          "id": "name",
          "label": "Имя",
          "type": "text",
          "required": true,
          "placeholder": "Ваше имя"
        },
        {
          "id": "phone",
          "label": "Телефон",
          "type": "tel",
          "required": true,
          "placeholder": "+7 (___) ___-__-__"
        },
        {
          "id": "field_edexu",
          "label": "Новое поле",
          "type": "city-dealer",
          "required": false,
          "placeholder": ""
        },
        {
          "id": "field_qwx0t",
          "label": "Новое поле",
          "type": "textarea",
          "required": false,
          "placeholder": ""
        }
      ],
      "backgroundColor": "#ffffff",
      "textColor": "#111111",
      "buttonColor": "#000000",
      "buttonTextColor": "#ffffff",
      "inputBackgroundColor": "#f3f4f6",
      "inputBorderColor": "transparent",
      "inputBorderWidth": 0,
      "layout": "standard",
      "formWidth": "default",
      "borderRadius": 16,
      "padding": 32,
      "maxWidth": 450,
      "showShadow": true,
      "animationType": "zoom",
      "cssSelector": ".btn-order, .btn-call",
      "createdAt": "2026-03-25T08:20:22.914Z",
      "isActive": true,
      "imageUrl": "",
      "imageFit": "cover",
      "hideImageOnMobile": false,
      "customWidth": 800
    },
    {
      "id": "dealer-form",
      "name": "Форма для карточки дилера",
      "title": "Связаться с дилером",
      "subtitle": "Оставьте заявку, и дилер свяжется с вами",
      "fields": [
        {
          "id": "dealer_info",
          "label": "Выбранный дилер",
          "type": "dealer-readonly",
          "required": false,
          "placeholder": ""
        },
        {
          "id": "name",
          "label": "Имя",
          "type": "text",
          "required": true,
          "placeholder": "Ваше имя"
        },
        {
          "id": "phone",
          "label": "Телефон",
          "type": "tel",
          "required": true,
          "placeholder": "+7 (___) ___-__-__"
        },
        {
          "id": "field_2py1y",
          "label": "Новое поле",
          "type": "model-select",
          "required": false,
          "placeholder": ""
        }
      ],
      "backgroundColor": "#ffffff",
      "textColor": "#111111",
      "buttonColor": "#000000",
      "buttonTextColor": "#ffffff",
      "inputBackgroundColor": "#f3f4f6",
      "inputBorderColor": "transparent",
      "inputBorderWidth": 0,
      "layout": "standard",
      "formWidth": "default",
      "borderRadius": 16,
      "padding": 32,
      "maxWidth": 450,
      "showShadow": true,
      "animationType": "slideUp",
      "cssSelector": ".btn-consult",
      "createdAt": "2026-03-25T09:20:22.914Z",
      "isActive": true,
      "imageUrl": "",
      "imageFit": "cover",
      "hideImageOnMobile": false,
      "customWidth": 800
    }
  ],
  "leads": [
    {
      "id": "lead-1",
      "form_id": "default-form",
      "name": "Иван Петров",
      "phone": "+7 (900) 123-45-67",
      "email": "ivan@example.com",
      "timestamp": "2026-03-25T07:20:22.915Z",
      "utm_source": "google",
      "utm_medium": "cpc",
      "utm_campaign": "search_brand",
      "status": "new",
      "type": "form",
      "notes": "Интересуется моделью X"
    },
    {
      "id": "lead-2",
      "form_id": "default-form",
      "name": "Мария Сидорова",
      "phone": "+7 (911) 987-65-43",
      "email": "maria@test.ru",
      "timestamp": "2026-03-24T08:20:22.915Z",
      "utm_source": "facebook",
      "utm_medium": "ads",
      "utm_campaign": "retargeting",
      "status": "in-progress",
      "type": "form",
      "notes": "Договорились о звонке завтра"
    },
    {
      "id": "lead-3",
      "form_id": "default-form",
      "name": "Алексей Смирнов",
      "phone": "+7 (922) 555-44-33",
      "timestamp": "2026-03-23T08:20:22.915Z",
      "utm_source": "yandex",
      "utm_medium": "direct",
      "status": "closed",
      "type": "call",
      "notes": "Сделка закрыта, оплата получена"
    },
    {
      "id": "lead-4",
      "name": "Елена Козлова",
      "phone": "+7 (933) 111-22-33",
      "timestamp": "2026-03-24T20:20:22.915Z",
      "utm_source": "google",
      "utm_medium": "organic",
      "status": "new",
      "type": "call",
      "notes": "Входящий звонок, интересовалась ценами"
    },
    {
      "id": "0nqbby70f",
      "form_id": "default-form",
      "session_id": "uia818fgx",
      "referrer": "",
      "page_url": "https://ais-dev-r2cioeyrddjhiq73cyubez-22975426076.us-west2.run.app/test-leadflow#",
      "product": "Проверьте работу LeadFlow прямо здесь.",
      "utm_source": null,
      "utm_medium": null,
      "utm_campaign": null,
      "utm_content": null,
      "utm_term": null,
      "name": "124",
      "phone": "2022",
      "city": "Москва",
      "dealer": "Дилер 2",
      "timestamp": "2026-03-25T08:23:16.379Z",
      "status": "new",
      "type": "form",
      "notes": ""
    },
    {
      "id": "jfbfysxew",
      "form_id": "default-form",
      "session_id": "uia818fgx",
      "referrer": "",
      "page_url": "https://ais-dev-r2cioeyrddjhiq73cyubez-22975426076.us-west2.run.app/test-leadflow#",
      "product": "Проверьте работу LeadFlow прямо здесь.",
      "utm_source": null,
      "utm_medium": null,
      "utm_campaign": null,
      "utm_content": null,
      "utm_term": null,
      "name": "223",
      "phone": "226",
      "city": "Екатеринбург",
      "dealer": "Дилер 5",
      "field_qwx0t": "Привет ",
      "timestamp": "2026-03-25T08:30:08.956Z",
      "status": "new",
      "type": "form",
      "notes": ""
    }
  ],
  "dealers": {
    "Москва": [
      {
        "name": "Дилер 1",
        "enabled": true
      },
      {
        "name": "Дилер 2",
        "enabled": true
      }
    ],
    "Санкт-Петербург": [
      {
        "name": "Дилер 3",
        "enabled": true
      },
      {
        "name": "Дилер 4",
        "enabled": true
      }
    ],
    "Екатеринбург": [
      {
        "name": "Дилер 5",
        "enabled": true
      }
    ]
  },
  "settings": {
    "bitrixWebhook": "",
    "yandexMetricaId": "95927232",
    "yandexMetricaToken": "9b53bd81cddd42700a30c9b9be1524b9",
    "yandexMetricaEnabled": true
  },
  "models": {
    "Мотоциклы": [
      {
        "name": "VOGE 300AC",
        "enabled": true
      },
      {
        "name": "VOGE 300R",
        "enabled": true
      },
      {
        "name": "VOGE 300RR",
        "enabled": true
      },
      {
        "name": "VOGE 500DS",
        "enabled": true
      },
      {
        "name": "VOGE 500DSX",
        "enabled": true
      },
      {
        "name": "VOGE 500R",
        "enabled": true
      },
      {
        "name": "VOGE 650DS",
        "enabled": true
      },
      {
        "name": "VOGE 650DSX",
        "enabled": true
      },
      {
        "name": "VOGE ER10",
        "enabled": true
      },
      {
        "name": "Loncin LX250",
        "enabled": true
      },
      {
        "name": "Loncin LX300",
        "enabled": true
      }
    ],
    "Квадроциклы": [
      {
        "name": "1000L",
        "enabled": true
      }
    ],
    "Скутер": [
      {
        "name": "450",
        "enabled": true
      }
    ]
  }
}